{
  "kind": "singleType",
  "collectionName": "whyjoininstients",
  "info": {
    "singularName": "whyjoininstient",
    "pluralName": "whyjoininstients",
    "displayName": "Whyjoininstient",
    "description": ""
  },
  "options": {
    "draftAndPublish": true
  },
  "pluginOptions": {},
  "attributes": {
    "Title": {
      "type": "string"
    },
    "header": {
      "type": "string"
    },
    "content1": {
      "type": "string"
    },
    "content1_answer": {
      "type": "text"
    },
    "content2": {
      "type": "string"
    },
    "content2_answer": {
      "type": "text"
    },
    "Image": {
      "type": "media",
      "multiple": false,
      "required": false,
      "allowedTypes": [
        "images",
        "files",
        "videos",
        "audios"
      ]
    },
    "Banner_Image1": {
      "allowedTypes": [
        "images",
        "files",
        "videos",
        "audios"
      ],
      "type": "media",
      "multiple": false
    },
    "Banner_Title1": {
      "type": "string"
    },
    "Banner_Description1": {
      "type": "string"
    },
    "Banner_Image2": {
      "allowedTypes": [
        "images",
        "files",
        "videos",
        "audios"
      ],
      "type": "media",
      "multiple": false
    },
    "Banner_Title2": {
      "type": "string"
    },
    "Banner_Description2": {
      "type": "string"
    }
  }
}
